<?xml version="1.0" encoding="utf-8"?>
<clothing-items>
 <clothing>
  <id>
   628739636
  </id>
  <name>
   Brooks Sweater E-9763
  </name>
  <category>
   Sweater
  </category>
  <size>
   XL
  </size>
  <color>
   Фиолетовый
  </color>
  <material>
   Кожа
  </material>
  <price>
   993918
  </price>
  <rating>
   4.19
  </rating>
  <reviews>
   530606
  </reviews>
  <exclusive>
   yes
  </exclusive>
  <sporty>
   no
  </sporty>
 </clothing>
 <clothing>
  <id>
   180505109
  </id>
  <name>
   Addidas T-shirt C-1864
  </name>
  <category>
   T-shirt
  </category>
  <size>
   XL
  </size>
  <color>
   Фиолетовый
  </color>
  <material>
   Шелк
  </material>
  <price>
   288609
  </price>
  <rating>
   4.66
  </rating>
  <reviews>
   278815
  </reviews>
  <exclusive>
   no
  </exclusive>
 </clothing>
 <clothing>
  <id>
   407894137
  </id>
  <name>
   Converse Gloves D-2335
  </name>
  <category>
   Gloves
  </category>
  <size>
   L
  </size>
  <color>
   Красный
  </color>
  <material>
   Полиэстер
  </material>
  <price>
   365482
  </price>
  <rating>
   3.0
  </rating>
  <reviews>
   620041
  </reviews>
  <new>
   +
  </new>
  <exclusive>
   no
  </exclusive>
  <sporty>
   no
  </sporty>
 </clothing>
 <clothing>
  <id>
   732234070
  </id>
  <name>
   Asics Gloves U-9864
  </name>
  <category>
   Gloves
  </category>
  <size>
   S
  </size>
  <color>
   Желтый
  </color>
  <material>
   Кожа
  </material>
  <price>
   955977
  </price>
  <rating>
   1.89
  </rating>
  <reviews>
   63732
  </reviews>
  <new>
   -
  </new>
  <exclusive>
   no
  </exclusive>
  <sporty>
   no
  </sporty>
 </clothing>
 <clothing>
  <id>
   540828696
  </id>
  <name>
   DC Shirt V-1916
  </name>
  <category>
   Shirt
  </category>
  <size>
   XXL
  </size>
  <color>
   Оранжевый
  </color>
  <material>
   Полиэстер
  </material>
  <price>
   493898
  </price>
  <rating>
   1.89
  </rating>
  <reviews>
   275056
  </reviews>
  <new>
   +
  </new>
  <sporty>
   yes
  </sporty>
 </clothing>
 <clothing>
  <id>
   482394667
  </id>
  <name>
   New Balance Jeans V-1392
  </name>
  <category>
   Jeans
  </category>
  <size>
   M
  </size>
  <color>
   Красный
  </color>
  <material>
   Шелк
  </material>
  <price>
   111277
  </price>
  <rating>
   2.36
  </rating>
  <reviews>
   973937
  </reviews>
  <exclusive>
   no
  </exclusive>
  <sporty>
   no
  </sporty>
 </clothing>
 <clothing>
  <id>
   637674876
  </id>
  <name>
   Converse Shoes X-8899
  </name>
  <category>
   Shoes
  </category>
  <size>
   XL
  </size>
  <color>
   Красный
  </color>
  <material>
   Хлопок
  </material>
  <price>
   453137
  </price>
  <rating>
   1.12
  </rating>
  <reviews>
   237360
  </reviews>
  <exclusive>
   no
  </exclusive>
  <sporty>
   no
  </sporty>
 </clothing>
 <clothing>
  <id>
   516471571
  </id>
  <name>
   Under Armour Belts G-7507
  </name>
  <category>
   Belts
  </category>
  <size>
   S
  </size>
  <color>
   Оранжевый
  </color>
  <material>
   Кожа
  </material>
  <price>
   828998
  </price>
  <rating>
   3.7
  </rating>
  <reviews>
   299770
  </reviews>
  <exclusive>
   no
  </exclusive>
 </clothing>
 <clothing>
  <id>
   233523084
  </id>
  <name>
   Vans Umbrellas J-5362
  </name>
  <category>
   Umbrellas
  </category>
  <size>
   XXL
  </size>
  <color>
   Оранжевый
  </color>
  <material>
   Кожа
  </material>
  <price>
   254899
  </price>
  <rating>
   3.42
  </rating>
  <reviews>
   989653
  </reviews>
  <new>
   -
  </new>
  <exclusive>
   no
  </exclusive>
  <sporty>
   yes
  </sporty>
 </clothing>
 <clothing>
  <id>
   891456880
  </id>
  <name>
   Addidas Gloves H-4564
  </name>
  <category>
   Gloves
  </category>
  <size>
   S
  </size>
  <color>
   Фиолетовый
  </color>
  <material>
   Шерсть
  </material>
  <price>
   206414
  </price>
  <rating>
   1.11
  </rating>
  <reviews>
   152682
  </reviews>
  <new>
   -
  </new>
  <exclusive>
   no
  </exclusive>
 </clothing>
 <clothing>
  <id>
   641141398
  </id>
  <name>
   Ellesse Jeans O-7303
  </name>
  <category>
   Jeans
  </category>
  <size>
   L
  </size>
  <color>
   Синий
  </color>
  <material>
   Нейлон
  </material>
  <price>
   271792
  </price>
  <rating>
   3.29
  </rating>
  <reviews>
   159014
  </reviews>
 </clothing>
 <clothing>
  <id>
   829729078
  </id>
  <name>
   Reebok Jeans X-2388
  </name>
  <category>
   Jeans
  </category>
  <size>
   XL
  </size>
  <color>
   Красный
  </color>
  <material>
   Вискоза
  </material>
  <price>
   424412
  </price>
  <rating>
   2.32
  </rating>
  <reviews>
   811232
  </reviews>
  <new>
   -
  </new>
  <exclusive>
   no
  </exclusive>
  <sporty>
   no
  </sporty>
 </clothing>
 <clothing>
  <id>
   238925579
  </id>
  <name>
   Converse Handbags A-9464
  </name>
  <category>
   Handbags
  </category>
  <size>
   L
  </size>
  <color>
   Зеленый
  </color>
  <material>
   Хлопок
  </material>
  <price>
   595481
  </price>
  <rating>
   4.33
  </rating>
  <reviews>
   723180
  </reviews>
  <new>
   -
  </new>
  <exclusive>
   no
  </exclusive>
  <sporty>
   no
  </sporty>
 </clothing>
 <clothing>
  <id>
   141399133
  </id>
  <name>
   New Balance Jeans E-3039
  </name>
  <category>
   Jeans
  </category>
  <size>
   L
  </size>
  <color>
   Голубой
  </color>
  <material>
   Лен
  </material>
  <price>
   417003
  </price>
  <rating>
   3.99
  </rating>
  <reviews>
   722773
  </reviews>
  <exclusive>
   no
  </exclusive>
  <sporty>
   no
  </sporty>
 </clothing>
 <clothing>
  <id>
   474764482
  </id>
  <name>
   DC Shoes O-4293
  </name>
  <category>
   Shoes
  </category>
  <size>
   M
  </size>
  <color>
   Красный
  </color>
  <material>
   Шерсть
  </material>
  <price>
   670839
  </price>
  <rating>
   2.72
  </rating>
  <reviews>
   460541
  </reviews>
  <new>
   +
  </new>
  <exclusive>
   yes
  </exclusive>
  <sporty>
   no
  </sporty>
 </clothing>
 <clothing>
  <id>
   480131302
  </id>
  <name>
   Under Armour Gloves U-5502
  </name>
  <category>
   Gloves
  </category>
  <size>
   XL
  </size>
  <color>
   Синий
  </color>
  <material>
   Шелк
  </material>
  <price>
   330927
  </price>
  <rating>
   2.64
  </rating>
  <reviews>
   446373
  </reviews>
  <new>
   +
  </new>
  <exclusive>
   no
  </exclusive>
 </clothing>
 <clothing>
  <id>
   914082010
  </id>
  <name>
   Lacoste Jacket P-1703
  </name>
  <category>
   Jacket
  </category>
  <size>
   M
  </size>
  <color>
   Фиолетовый
  </color>
  <material>
   Нейлон
  </material>
  <price>
   632925
  </price>
  <rating>
   4.56
  </rating>
  <reviews>
   856545
  </reviews>
  <new>
   -
  </new>
  <exclusive>
   yes
  </exclusive>
  <sporty>
   yes
  </sporty>
 </clothing>
 <clothing>
  <id>
   771935337
  </id>
  <name>
   Brooks Dress X-6322
  </name>
  <category>
   Dress
  </category>
  <size>
   XXL
  </size>
  <color>
   Фиолетовый
  </color>
  <material>
   Вискоза
  </material>
  <price>
   697406
  </price>
  <rating>
   4.67
  </rating>
  <reviews>
   687761
  </reviews>
  <new>
   -
  </new>
  <exclusive>
   no
  </exclusive>
 </clothing>
 <clothing>
  <id>
   609530548
  </id>
  <name>
   PleinSport Shoes J-7211
  </name>
  <category>
   Shoes
  </category>
  <size>
   L
  </size>
  <color>
   Синий
  </color>
  <material>
   Нейлон
  </material>
  <price>
   147678
  </price>
  <rating>
   3.24
  </rating>
  <reviews>
   936476
  </reviews>
  <exclusive>
   yes
  </exclusive>
  <sporty>
   no
  </sporty>
 </clothing>
 <clothing>
  <id>
   642838102
  </id>
  <name>
   Ellesse Gloves Y-3412
  </name>
  <category>
   Gloves
  </category>
  <size>
   XL
  </size>
  <color>
   Голубой
  </color>
  <material>
   Нейлон
  </material>
  <price>
   227948
  </price>
  <rating>
   4.63
  </rating>
  <reviews>
   476799
  </reviews>
  <new>
   -
  </new>
  <sporty>
   no
  </sporty>
 </clothing>
 <clothing>
  <id>
   381008772
  </id>
  <name>
   Ellesse Umbrellas U-2175
  </name>
  <category>
   Umbrellas
  </category>
  <size>
   XXL
  </size>
  <color>
   Красный
  </color>
  <material>
   Лен
  </material>
  <price>
   796545
  </price>
  <rating>
   4.51
  </rating>
  <reviews>
   149626
  </reviews>
  <new>
   +
  </new>
  <exclusive>
   no
  </exclusive>
 </clothing>
</clothing-items>
